cloudchain/__init__.py
cloudchain/__main__.py
cloudchain/cli.py
cloudchain/core.py
cloudchain_cli-0.1.1.dist-info/licenses/LICENSE.md
cloudchain_cli-0.1.1.dist-info/METADATA
cloudchain_cli-0.1.1.dist-info/WHEEL
cloudchain_cli-0.1.1.dist-info/entry_points.txt
cloudchain_cli-0.1.1.dist-info/top_level.txt
cloudchain_cli-0.1.1.dist-info/RECORD
