Metadata-Version: 2.4
Name: cloudchain-cli
Version: 0.1.1
Summary: Deterministic Google Drive backup manager with chained accounts and encrypted state.
Author-email: Christopher Hirschauer <you@example.com>
License: CloudChain License
Project-URL: Homepage, https://github.com/74Thirsty/CloudChain
Project-URL: Source, https://github.com/74Thirsty/CloudChain
Project-URL: Issues, https://github.com/74Thirsty/CloudChain/issues
Project-URL: Documentation, https://github.com/74Thirsty/CloudChain#readme
Classifier: Programming Language :: Python :: 3
Classifier: Programming Language :: Python :: 3.9
Classifier: License :: Other/Proprietary License
Classifier: Environment :: Console
Classifier: Operating System :: OS Independent
Classifier: Topic :: System :: Archiving :: Backup
Requires-Python: >=3.9
License-File: LICENSE.md
Requires-Dist: google-api-python-client
Requires-Dist: google-auth-oauthlib
Requires-Dist: google-auth
Requires-Dist: keyring
Requires-Dist: PyYAML
Requires-Dist: cryptography
Requires-Dist: rich
Dynamic: license-file
